{
  "prefs": {
    "CrashReportingEnabled": "true",
    "CursorBlink": "\"Enabled\"",
    "AgentModeOnboardingBlockShown": "true",
    "WelcomeTipsFeaturesUsed": "[{\"Action\":\"SplitPane\"},{\"Hint\":\"CreateBlock\"},{\"Action\":\"ThemePicker\"},{\"Hint\":\"BlockAction\"},{\"Action\":\"CommandPalette\"},{\"Hint\":\"BlockSelect\"},{\"Action\":\"CommandSearch\"}]",
    "ExperimentId": "8714811d-d12b-4ba4-a8ef-6c961897eced",
    "Theme": "\"Dracula\"",
    "ShowWarningBeforeLogOut": "true",
    "ReceivedReferralTheme": "\"Inactive\"",
    "ShowIndicatorsButton": "true",
    "ShowChangelogAfterUpdate": "true",
    "TelemetryEnabled": "true",
    "OpenWindowsAtCustomSize": "false",
    "FocusPaneOnHover": "false",
    "Shortcuts": "true",
    "FontName": "\"JetBrains Mono\"",
    "AltScreenPadding": "{\"Custom\":{\"uniform_padding\":0.0}}",
    "Notifications": "{\"mode\":\"Enabled\",\"is_long_running_enabled\":true,\"long_running_threshold\":{\"secs\":30,\"nanos\":0},\"is_password_prompt_enabled\":true}",
    "ShouldDimInactivePanes": "false",
    "AutosuggestionAcceptedCount": "2",
    "HasAutoOpenedWelcomeFolder": "true",
    "EnforceMinimumContrast": "\"OnlyNamedColors\"",
    "AIAssistantRequestLimitInfo": "{\"limit\":100,\"num_requests_used_since_refresh\":38,\"next_refresh_time\":\"2024-11-03T01:08:42.618598Z\",\"is_unlimited\":false}",
    "ChangelogVersions": "{\"v0.2024.10.23.14.49.stable_00\":true,\"v0.2024.10.29.08.02.stable_02\":true,\"v0.2024.11.05.08.02.stable_02\":true,\"v0.2024.11.12.08.02.stable_02\":true,\"v0.2024.11.19.08.02.stable_01\":true,\"v0.2024.11.19.08.02.stable_03\":true}",
    "InputAutodetectionBannerDismissed": "true",
    "NotebookFontSize": "14.0",
    "AIAutoDetectionEnabled": "true",
    "SystemTheme": "true",
    "SameLinePromptBlockState": "\"DoNotShow\"",
    "AIRequestLimitInfo": "{\"limit\":100,\"num_requests_used_since_refresh\":2,\"next_refresh_time\":\"2025-01-05T00:12:44.997550Z\",\"is_unlimited\":false}",
    "Spacing": "\"Normal\"",
    "SelectedSystemThemes": "{\"light\":\"Light\",\"dark\":\"Dracula\"}",
    "FontSize": "13.0",
    "HonorPS1": "true",
    "InputMode": "\"Waterfall\"",
    "ShowWarningBeforeQuitting": "true",
    "OverrideOpacity": "32",
    "AliasExpansionBannerSeen": "true"
  }
}